final_project_group9/detector.v
 module seq_detector(
    din,
    clk,
    reset,
    z
 );

 output reg z;
 input din,clk,reset;

  parameter [2:0] S0 = 3'd0;  //1
  parameter [2:0] S1 = 3'd1;  //0
  parameter [2:0] S2 = 3'd2;  //00
  parameter [2:0] S3 = 3'd3;  //000
  parameter [2:0] S4 = 3'd4;  //001 or 0001
  //3'b001沒有標

  reg [2:0] PS,NS ;//2bits

  //sequential state register block
 always @ (posedge clk or posedge reset)
 //begin
   if (reset)
     PS <= S0;  
   else
     PS <= NS;
 //end

//sequential output block
 always @ (*)//學長提示
  // begin
    if (reset)
    z <= 1'b0;
    else 
        case(PS)
        S0 : z <= 1'b0;
        S1 : z <= 1'b0;
        S2 : z <= 1'b0;
        S3 : if(din)
             z <=1'b1;
             else
             z <=1'b0;
        S4 : if(din)
             z <=1'b0;
             else
             z <=1'b1;
        default:z <=1'b0;
        endcase
   // end
     
  //combinational state assignment block  
 always @ (*)
  begin
    case(PS)
        S0 : NS = din ? S0 : S1 ;
        S1 : NS = din ? S0 : S2 ;
        S2 : NS = din ? S4 : S3 ;
        S3 : NS = din ? S4 : S3 ;
        S4 : NS = din ? S0 : S1 ;
    endcase
    $monitor("present state is %d",PS);
  end
 
 endmodule

final_project_group9/testbench.v
`timescale 1ns / 10ps
`define CYCLE      25.0          	  // Modify your clock period here
`define End_CYCLE  26                 // Modify cycle times once your design need more cycle times!  
`include "detector.v"
module testbench;

    // Inputs
    reg in_data;
    reg clk;
    reg reset;
    reg mem_i [18:0];//input signal
    reg correct [18:0];//correct signal
    // Outputs
    wire out_data;


    integer i;
    integer error;
    // name the test: first_case
    seq_detector first_case (
        .din(in_data), 
        .clk(clk), 
        .reset(reset), 
        .z(out_data)
    );

    always begin #(`CYCLE/2) clk = ~clk; end // let the clk be opposite every half cycle 

    initial begin
    $dumpfile("dump.vcd");
    $dumpvars(0, testbench);
    $readmemh("input.txt",mem_i);// time = 0   (file 自己要放好)
    $readmemh("correct.txt",correct);// time = 0(file 自己要放好)
    $display("-----------------------------------------------------");// time = 0
    $display("START!!! Simulation Start .....");                      // time = 0
    $display("-----------------------------------------------------");// time = 0
    end

    initial begin
            clk = 1'b1;                         // time = 0
            reset = 1'b1;                       // time = 0
            in_data = 1'b0;                     // time = 0
            error = 0;                          // time = 0
            #(`CYCLE) reset = 1'b0;             // time = a cycle
            #(`CYCLE*`End_CYCLE) $finish;       // time = a cycle(above) + End_CYCLE*CYCLE
        end

    initial begin
            case1;      //start at time = 0;
        end

    // task block ack like a function in software, it will run squentially inside the block
        task case1; begin
            wait(reset==0);             // stall here untill reset become '0' (correspond to line 47)
            for(i=0;i<19;i++) begin
                in_data = mem_i[i];
                # 0.01;                 // wait for a moment for taking wanted value (if not will get the pre-cycle's value)
                if(out_data==correct[i]) begin
                    $display("input= %d, out data equal to %d",in_data,correct[i]);
                end
                else begin
                    $display("input= %d, out data is %d but correct_output is %d",in_data,out_data,correct[i]);
                    error = 1;
                end
                @(posedge clk);         // stall here until the next clock posedge
            end

            if(error) begin
                $display("-----------------------------------------------------");
                $display("Simulation END, there are some errors.....");
                $display("-----------------------------------------------------");
            end
            else begin
                $display("-----------------------------------------------------");
                $display("Simulation END, SUCCESS!!!");
                $display("-----------------------------------------------------");
            end
            //test reset
            reset=1'b1;
            wait(reset==1);
                $display("-----------------------------------------------------");
                $display("-------------------now reset-------------------------");
            # 0.01;
            reset=1'b0;
            wait(reset==0);
                $display("after reset state is S0");
                $display("below:after reset in_data is always 0 ,state S0->S1->S2->S3");             
        end endtask



endmodule

final_project_group9/dump.vcd
$date
	Mon Jun 21 22:36:47 2021
$end
$version
	Icarus Verilog
$end
$timescale
	10ps
$end
$scope module testbench $end
$var wire 1 ! out_data $end
$var reg 1 " clk $end
$var reg 1 # in_data $end
$var reg 1 $ reset $end
$var integer 32 % error [31:0] $end
$var integer 32 & i [31:0] $end
$scope module first_case $end
$var wire 1 " clk $end
$var wire 1 # din $end
$var wire 1 $ reset $end
$var reg 3 ' NS [2:0] $end
$var reg 3 ( PS [2:0] $end
$var reg 1 ! z $end
$upscope $end
$scope task case1 $end
$upscope $end
$upscope $end
$enddefinitions $end
#0
$dumpvars
b0 (
b1 '
bx &
b0 %
1$
0#
1"
0!
$end
#1250
0"
#2500
b1 (
b0 '
1#
b0 &
1"
0$
#3750
0"
#5000
b0 (
b1 &
1"
#6250
0"
#7500
b1 '
0#
b10 &
1"
#8750
0"
#10000
b10 '
b1 (
b11 &
1"
#11250
0"
#12500
b10 (
b100 '
1#
b100 &
1"
#13750
0"
#15000
1!
b100 (
b1 '
0#
b101 &
1"
#16250
0"
#17500
0!
b10 '
b1 (
b110 &
1"
#18750
0"
#20000
b10 (
b100 '
1#
b111 &
1"
#21250
0"
#22500
b0 '
b100 (
b1000 &
1"
#23750
0"
#25000
0!
b0 (
b1 '
0#
b1001 &
1"
#26250
0"
#27500
b10 '
b1 (
b1010 &
1"
#28750
0"
#30000
b11 '
b10 (
b1011 &
1"
#31250
0"
#32500
1!
b11 (
b100 '
1#
b1100 &
1"
#33750
0"
#35000
1!
b100 (
b1 '
0#
b1101 &
1"
#36250
0"
#37500
0!
b10 '
b1 (
b1110 &
1"
#38750
0"
#40000
b11 '
b10 (
b1111 &
1"
#41250
0"
#42500
b11 (
b10000 &
1"
#43750
0"
#45000
1!
b100 '
1#
b10001 &
1"
#46250
0"
#47500
1!
b100 (
b1 '
0#
b10010 &
1"
#48750
0"
#50000
0!
b0 (
1$
b10011 &
1"
#50001
0$
#51250
0"
#52500
b10 '
b1 (
1"
#53750
0"
#55000
b11 '
b10 (
1"
#56250
0"
#57500
b11 (
1"
